robertcommondriver/__init__.py
robertcommondriver/system/__init__.py
robertcommondriver/system/driver/__init__.py
robertcommondriver/system/driver/bacnet.py
robertcommondriver/system/driver/bacnetc.py
robertcommondriver/system/driver/base.py
robertcommondriver/system/driver/iec104.py
robertcommondriver/system/driver/modbus.py
robertcommondriver/system/driver/obix.py
robertcommondriver/system/driver/opcda.py
robertcommondriver/system/driver/opcda_openopc.py
robertcommondriver/system/driver/opcua.py
robertcommondriver/system/driver/plcs7.py
robertcommondriver/system/driver/snmp.py
robertcommondriver/system/iot/__init__.py
robertcommondriver/system/iot/base.py
robertcommondriver/system/iot/iot_bacnet.py
robertcommondriver/system/iot/iot_bacnet_mstp.py
robertcommondriver/system/iot/iot_iec104.py
robertcommondriver/system/iot/iot_modbus.py
robertcommondriver/system/iot/iot_obix.py
robertcommondriver/system/iot/iot_opcda.py
robertcommondriver/system/iot/iot_opcua.py
robertcommondriver/system/iot/iot_plc_ab.py
robertcommondriver/system/iot/iot_plc_mitsubishi.py
robertcommondriver/system/iot/iot_plc_omron.py
robertcommondriver/system/iot/iot_plc_s7.py
robertcommondriver/system/iot/iot_plc_siemens.py
robertcommondriver/system/iot/iot_snmp.py
tests/__init__.py
tests/test_system/__init__.py
tests/test_system/test_driver/__init__.py
tests/test_system/test_driver/test_bacnet.py
tests/test_system/test_driver/test_bacnet1.py
tests/test_system/test_driver/test_bacnetc.py
tests/test_system/test_driver/test_bacnetv1.py
tests/test_system/test_driver/test_modbus.py
tests/test_system/test_driver/test_obix.py
tests/test_system/test_driver/test_opcda.py
tests/test_system/test_driver/test_opcua.py
tests/test_system/test_driver/test_plcs7.py
tests/test_system/test_driver/test_snmp.py
tests/test_system/test_iot/__init__.py
tests/test_system/test_iot/test_bacnet1.py
tests/test_system/test_iot/test_iot_bacnet.py
tests/test_system/test_iot/test_iot_bacnet_mstp.py
robertcommondriver-0.1.76.dist-info/LICENSE
robertcommondriver-0.1.76.dist-info/METADATA
robertcommondriver-0.1.76.dist-info/WHEEL
robertcommondriver-0.1.76.dist-info/top_level.txt
robertcommondriver-0.1.76.dist-info/RECORD
