Metadata-Version: 2.1
Name: robertcommondriver
Version: 0.1.76
Summary: Robert Common Driver Library
Home-page: https://github.com/hun0423/RobertCommonDriver
Author: Robert0423
Author-email: 851010070@qq.com
License: MIT
Classifier: License :: OSI Approved :: MIT License
Classifier: Programming Language :: Python
Classifier: Programming Language :: Python :: 3
Classifier: Programming Language :: Python :: 3.6
Classifier: Programming Language :: Python :: Implementation :: CPython
Classifier: Programming Language :: Python :: Implementation :: PyPy
Requires-Python: >=3.6.0
License-File: LICENSE
Requires-Dist: bacpypes (==0.18.6)
Requires-Dist: construct (==2.5.2)
Requires-Dist: func-timeout
Requires-Dist: modbus-tk (==1.1.2)
Requires-Dist: opcua (==0.98.13)
Requires-Dist: OpenOPC-Python3x (==1.3.1)
Requires-Dist: psutil
Requires-Dist: Pyro4 (>=4.81)
Requires-Dist: Pyro5 (>=5.14)
Requires-Dist: pyserial
Requires-Dist: pysnmp (==4.4.12)
Requires-Dist: python-dateutil
Requires-Dist: python-snap7 (==1.3)
Requires-Dist: requests
Requires-Dist: scapy (>=2.4.5)
